aijson_pdf/__init__.py
aijson_pdf/actions/__init__.py
aijson_pdf/actions/extract_pdf_text.py
aijson_pdf/actions/ocr.py
aijson_pdf/tests/__init__.py
aijson_pdf/tests/conftest.py
aijson_pdf-0.1.1.dist-info/LICENSE
aijson_pdf-0.1.1.dist-info/METADATA
aijson_pdf-0.1.1.dist-info/WHEEL
aijson_pdf-0.1.1.dist-info/entry_points.txt
aijson_pdf-0.1.1.dist-info/RECORD
